pydeconv/__init__.py
pydeconv/model/README.md
pydeconv/model/__init__.py
pydeconv/model/base_model.py
pydeconv/model/mixupvi.py
pydeconv/model/nnls.py
pydeconv/model/ols.py
pydeconv/model/rlr.py
pydeconv/model/scaden.py
pydeconv/model/svr.py
pydeconv/model/tape.py
pydeconv/model/wls.py
pydeconv/model/nn/__init__.py
pydeconv/model/nn/mixupvi.py
pydeconv/model/nn/registry.py
pydeconv/model/nn/scaden.py
pydeconv/model/nn/tape.py
pydeconv/model/nn/scvi/module_mixupvae.py
pydeconv/model/solver/__init__.py
pydeconv/model/solver/linear.py
pydeconv/model/solver/nn.py
pydeconv/model/solver/svm.py
pydeconv/signature_matrix/__init__.py
pydeconv/signature_matrix/registry.py
pydeconv/signature_matrix/signature_matrix.py
pydeconv/utils/__init__.py
pydeconv/utils/hub.py
pydeconv/utils/licence.py
pydeconv/utils/optional_imports.py
pydeconv/utils/reproducibility.py
pydeconv/utils/validator.py
pydeconv-0.0.7.dist-info/METADATA
pydeconv-0.0.7.dist-info/WHEEL
pydeconv-0.0.7.dist-info/licenses/LICENSE
pydeconv-0.0.7.dist-info/RECORD
