Metadata-Version: 2.4
Name: pydeconv
Version: 0.0.7
Summary: Python implementation of deconvolution algorithms
Project-URL: Source, https://github.com/owkin/PyDeconv
Project-URL: Documentation, https://owkin.github.io/PyDeconv/
Project-URL: Issues, https://github.com/owkin/PyDeconv/issues
Author-email: Yann Rodriguez <yann.rodriguez@owkin.com>
License-File: LICENSE
Classifier: Development Status :: 4 - Beta
Classifier: Intended Audience :: Developers
Classifier: Intended Audience :: Science/Research
Classifier: Natural Language :: English
Classifier: Programming Language :: Python :: 3
Classifier: Programming Language :: Python :: 3.10
Classifier: Programming Language :: Python :: 3.11
Classifier: Programming Language :: Python :: 3.12
Classifier: Topic :: Scientific/Engineering
Classifier: Topic :: Software Development
Classifier: Topic :: Software Development :: Libraries
Classifier: Topic :: Software Development :: Libraries :: Application Frameworks
Classifier: Topic :: Software Development :: Libraries :: Python Modules
Requires-Python: >=3.10
Requires-Dist: anndata>=0.11.2
Requires-Dist: cvxopt>=1.3.2
Requires-Dist: loguru>=0.7.3
Requires-Dist: matplotlib>=3.10.0
Requires-Dist: mkdocs-dracula-theme>=1.0.7
Requires-Dist: quadprog>=0.1.13
Requires-Dist: requests>=2.32.3
Requires-Dist: scikit-learn>=1.6.1
Requires-Dist: statsmodels>=0.14.4
Requires-Dist: tqdm>=4.67.1
Provides-Extra: scvi
Requires-Dist: scvi-tools[autotune]>=1.3.1.post1; extra == 'scvi'
Provides-Extra: torch
Requires-Dist: torch>=2.6.0; extra == 'torch'
